unifydoc/__init__.py
unifydoc/cli.py
unifydoc-0.1.1.dist-info/METADATA
unifydoc-0.1.1.dist-info/WHEEL
unifydoc-0.1.1.dist-info/top_level.txt
unifydoc-0.1.1.dist-info/RECORD
