Metadata-Version: 2.4
Name: unifydoc
Version: 0.1.1
Summary: Unified document processing with AI-powered OCR
Home-page: https://github.com/luisleo526/unifydoc
Author: HaoLiangWen
Author-email: UnifyDoc Team <luisleo52655@gmail.com>
Maintainer-email: UnifyDoc Team <luisleo52655@gmail.com>
License: MIT
Project-URL: Homepage, https://github.com/luisleo526/unifydoc
Project-URL: Documentation, https://unifydoc.readthedocs.io
Project-URL: Repository, https://github.com/luisleo526/unifydoc
Project-URL: Issues, https://github.com/luisleo526/unifydoc/issues
Project-URL: Changelog, https://github.com/luisleo526/unifydoc/blob/main/CHANGELOG.md
Keywords: document-processing,ocr,pdf,docx,xlsx,pptx,ai,gpt-4,openai,langchain,document-extraction,text-extraction
Classifier: Development Status :: 4 - Beta
Classifier: Intended Audience :: Developers
Classifier: License :: OSI Approved :: MIT License
Classifier: Operating System :: OS Independent
Classifier: Programming Language :: Python :: 3
Classifier: Programming Language :: Python :: 3.8
Classifier: Programming Language :: Python :: 3.9
Classifier: Programming Language :: Python :: 3.10
Classifier: Programming Language :: Python :: 3.11
Classifier: Programming Language :: Python :: 3.12
Classifier: Topic :: Software Development :: Libraries :: Python Modules
Classifier: Topic :: Text Processing
Classifier: Topic :: Scientific/Engineering :: Artificial Intelligence
Requires-Python: >=3.8
Requires-Dist: pymupdf>=1.23.0
Requires-Dist: python-docx>=0.8.11
Requires-Dist: openpyxl>=3.0.10
Requires-Dist: python-pptx>=0.6.21
Requires-Dist: beautifulsoup4>=4.12.0
Requires-Dist: lxml>=4.9.0
Requires-Dist: markdown>=3.4.0
Requires-Dist: chardet>=5.0.0
Requires-Dist: Pillow>=9.0.0
Requires-Dist: pandas>=1.3.0
Provides-Extra: ocr
Requires-Dist: openai>=1.0.0; extra == "ocr"
Requires-Dist: langchain>=0.1.0; extra == "ocr"
Requires-Dist: langchain-openai>=0.0.2; extra == "ocr"
Requires-Dist: pytesseract>=0.3.10; extra == "ocr"
Provides-Extra: all
Requires-Dist: unifydoc[ocr]; extra == "all"
Provides-Extra: dev
Requires-Dist: pytest>=7.0.0; extra == "dev"
Requires-Dist: pytest-cov>=4.0.0; extra == "dev"
Requires-Dist: pytest-xdist>=3.0.0; extra == "dev"
Requires-Dist: pytest-timeout>=2.0.0; extra == "dev"
Requires-Dist: black>=23.0.0; extra == "dev"
Requires-Dist: isort>=5.0.0; extra == "dev"
Requires-Dist: flake8>=6.0.0; extra == "dev"
Requires-Dist: mypy>=1.0.0; extra == "dev"
Requires-Dist: pre-commit>=3.0.0; extra == "dev"
Requires-Dist: twine>=4.0.0; extra == "dev"
Requires-Dist: build>=0.10.0; extra == "dev"
Provides-Extra: docs
Requires-Dist: sphinx>=6.0.0; extra == "docs"
Requires-Dist: sphinx-rtd-theme>=1.3.0; extra == "docs"
Requires-Dist: sphinx-autodoc-typehints>=1.23.0; extra == "docs"
Requires-Dist: myst-parser>=2.0.0; extra == "docs"
Dynamic: author
Dynamic: home-page
Dynamic: requires-python
